mothership/__init__.py
mothership/client.py
mothership/exceptions.py
mothership/test_client.py
mothership_client-1.0.0.dist-info/LICENSE
mothership_client-1.0.0.dist-info/METADATA
mothership_client-1.0.0.dist-info/WHEEL
mothership_client-1.0.0.dist-info/top_level.txt
mothership_client-1.0.0.dist-info/RECORD
