Metadata-Version: 2.1
Name: mothership-client
Version: 1.0.0
Summary: The official Mothership configuration client for Python
Home-page: https://github.com/spicket/mothership-client-python
Author: Mothership
Author-email: dev@spicket.io
License: MIT
Download-URL: https://github.com/spicket/mothership-client-python/tarball/1.0.0
Platform: UNKNOWN
Requires-Dist: requests
